tess/__init__.py
tess/_version.py
tess/location/__init__.py
tess/location/cli.py
tess/location/dao.py
tess/location/parser.py
tess/logfile/__init__.py
tess/logfile/cli.py
tess/logfile/dao.py
tess/logfile/logfile.py
tess/logfile/parser.py
tess/observer/__init__.py
tess/observer/cli.py
tess/observer/dao.py
tess/observer/parser.py
tess/photometer/__init__.py
tess/photometer/parser.py
tess/photometer/asyncio/__init__.py
tess/photometer/asyncio/cli.py
tess/photometer/asyncio/dao.py
tess/photometer/noasync/__init__.py
tess/photometer/noasync/cli.py
tess/photometer/noasync/dao.py
tessdb_cmdline-0.4.1.dist-info/licenses/LICENSE
tessdb_cmdline-0.4.1.dist-info/METADATA
tessdb_cmdline-0.4.1.dist-info/WHEEL
tessdb_cmdline-0.4.1.dist-info/entry_points.txt
tessdb_cmdline-0.4.1.dist-info/top_level.txt
tessdb_cmdline-0.4.1.dist-info/RECORD
