Metadata-Version: 2.4
Name: tessdb-cmdline
Version: 0.4.1
Summary: TESS database command line tools
Author-email: Rafael González <rafael08@ucm.es>
Project-URL: Homepage, https://github.com/STARS4ALL/tessdb-cmdline-ng
Project-URL: Repository, https://github.com/STARS4ALL/tessdb-cmdline-ng.git
Classifier: Programming Language :: Python :: 3.12
Classifier: Programming Language :: SQL
Classifier: Development Status :: 4 - Beta
Classifier: Environment :: Console
Classifier: Operating System :: POSIX :: Linux
Classifier: Topic :: Scientific/Engineering :: Astronomy
Classifier: Topic :: Scientific/Engineering :: Atmospheric Science
Classifier: Intended Audience :: Science/Research
Classifier: Intended Audience :: Developers
Classifier: Natural Language :: English
Classifier: Natural Language :: Spanish
Requires-Python: >=3.12
License-File: LICENSE
Requires-Dist: sqlalchemy[asyncio]>=2.0
Requires-Dist: lica[aiosqlalchemy]>=2.0
Requires-Dist: aiosqlite
Requires-Dist: tessdb-dao>=0.4
Requires-Dist: tessdb-api>=0.4
Requires-Dist: zptess-dao>=1.0
Provides-Extra: test
Requires-Dist: pytest>=6; extra == "test"
Dynamic: license-file
